discordrp_pcsx2n/__init__.py
discordrp_pcsx2n/utils.py
discordrp_pcsx2n-0.1.1.dist-info/entry_points.txt
discordrp_pcsx2n-0.1.1.dist-info/WHEEL
discordrp_pcsx2n-0.1.1.dist-info/METADATA
discordrp_pcsx2n-0.1.1.dist-info/RECORD
